myFirstPackage/Computation.py
myFirstPackage/__init__.py
myFirstPackage/integrators/__init__.py
myFirstPackage/integrators/integrators.py
myFirstPackage_TrialGuyOne-0.1.0.dev10.dist-info/METADATA
myFirstPackage_TrialGuyOne-0.1.0.dev10.dist-info/RECORD
myFirstPackage_TrialGuyOne-0.1.0.dev10.dist-info/WHEEL
myFirstPackage_TrialGuyOne-0.1.0.dev10.dist-info/top_level.txt
