Metadata-Version: 2.1
Name: myFirstPackage-TrialGuyOne
Version: 0.1.0.dev10
Summary: A Simple Python Package for studying and Learning Python
Home-page: https://gitlab.com/TheOnlyTrialMan/TheFirstPythonPackage.git
Author: Trial Man
Author-email: UNKNOWN
License: UNKNOWN
Platform: UNKNOWN
Requires-Dist: numpy
